auto_abi_checker/__init__.py
auto_abi_checker/abi_executor.py
auto_abi_checker/auto-abi.py
auto_abi_checker/generator.py
auto_abi_checker/ros_utils.py
auto_abi_checker/srcs_apt.py
auto_abi_checker/srcs_base.py
auto_abi_checker/srcs_local.py
auto_abi_checker/srcs_ros.py
auto_abi_checker/utils.py
auto_abi_checker-0.1.10.data/scripts/auto-abi.py
auto_abi_checker-0.1.10.dist-info/DESCRIPTION.rst
auto_abi_checker-0.1.10.dist-info/METADATA
auto_abi_checker-0.1.10.dist-info/RECORD
auto_abi_checker-0.1.10.dist-info/WHEEL
auto_abi_checker-0.1.10.dist-info/metadata.json
auto_abi_checker-0.1.10.dist-info/top_level.txt
