Metadata-Version: 2.0
Name: auto-abi-checker
Version: 0.1.10
Summary: Tool to facilitate the run of abi-compliance-checker
Home-page: https://github.com/osrf/auto-abi-checker
Author: Jose Luis Rivero
Author-email: jrivero@osrfoundation.org
License: Apache License 2.0
Download-URL: https://github.com/osrf/auto-abi-checker/archive/0.1.10.tar.gz
Platform: UNKNOWN
Classifier: Development Status :: 3 - Alpha
Classifier: Intended Audience :: Developers
Classifier: Programming Language :: Python
Classifier: Programming Language :: Python :: 3
Classifier: License :: OSI Approved :: Apache Software License
Requires-Python: >=3.0
Requires-Dist: docopt
Requires-Dist: rosdistro
